pythonverse/__init__.py
pythonverse/example.py
pythonverse-0.0.2.dist-info/METADATA
pythonverse-0.0.2.dist-info/WHEEL
pythonverse-0.0.2.dist-info/licenses/LICENSE
pythonverse-0.0.2.dist-info/RECORD
